{
    "type": "result",
    "timestamp": "2020-01-26T11:27:30Z",
    "ping": {
        "jitter": 0.117,
        "latency": 306.509
    },
    "download": {
        "bandwidth": 1494315,
        "bytes": 13034000,
        "elapsed": 12309
    },
    "upload": {
        "bandwidth": 398345,
        "bytes": 4919600,
        "elapsed": 15009
    },
    "packetLoss": 0,
    "isp": "Mauritius Telecom",
    "server": {
        "id": 24682,
        "name": "Vodafone India",
        "location": "Cochin",
        "country": "India",
        "host": "ooklatestcochin.live.vodafone.in",
        "port": 8080,
        "ip": "112.79.47.25"
    },
    "result": {
        "id": "147e5da0-7b42-4aa9-8f25-32d104c46395",
        "url": "https://www.speedtest.net/result/c/147e5da0-7b42-4aa9-8f25-32d104c46395"
    }
}